IndicatorTypes.py
OTXv2.py
patch_pulse.py
OTXv2-1.5.12.dist-info/LICENSE
OTXv2-1.5.12.dist-info/METADATA
OTXv2-1.5.12.dist-info/WHEEL
OTXv2-1.5.12.dist-info/top_level.txt
OTXv2-1.5.12.dist-info/RECORD
